retranslator/Translator.py
retranslator/TranslatorCLI.py
retranslator/__init__.py
retranslator-0.1.2.dist-info/METADATA
retranslator-0.1.2.dist-info/WHEEL
retranslator-0.1.2.dist-info/top_level.txt
retranslator-0.1.2.dist-info/RECORD
