Metadata-Version: 2.1
Name: retranslator
Version: 0.1.2
Summary: retranslator
Home-page: https://github.com/linksplatform/RegularExpressions.Transformer/tree/master/python
Author: Ethosa
Author-email: social.ethosa@gmail.com
License: LGPLv3
Project-URL: Github, https://github.com/linksplatform/RegularExpressions.Transformer/tree/master/python
Project-URL: Documentation, https://github.com/linksplatform/RegularExpressions.Transformer/tree/master/python
Keywords: csharp cpp cs2cpp platform ethosa konard retranslator
Platform: UNKNOWN
Classifier: Development Status :: 4 - Beta
Classifier: Programming Language :: Python :: 3
Classifier: Programming Language :: Python :: 3.4
Classifier: Programming Language :: Python :: 3.5
Classifier: Programming Language :: Python :: 3.6
Classifier: Programming Language :: Python :: 3.7
Classifier: License :: OSI Approved :: GNU Lesser General Public License v3 (LGPLv3)
Classifier: Operating System :: OS Independent
Requires-Python: >=3
Requires-Dist: regex
